illallangi/mastodon/__init__.py
illallangi/mastodon/__version__.py
illallangi/mastodon/tools.py
illallangi/mastodon/adapters/__init__.py
illallangi/mastodon/adapters/fitness.py
illallangi/mastodon/adapters/mastodon.py
illallangi/mastodon/client/__init__.py
illallangi/mastodon/client/swim_statistics.py
illallangi/mastodon/client/swims.py
illallangi/mastodon/diffsyncmodels/__init__.py
illallangi/mastodon/diffsyncmodels/status.py
illallangi/mastodon/diffsyncmodels/swim.py
illallangi/mastodon/models/__init__.py
illallangi/mastodon/models/status.py
illallangi/mastodon/models/swim.py
illallangi_mastodon-0.4.0.dist-info/METADATA
illallangi_mastodon-0.4.0.dist-info/WHEEL
illallangi_mastodon-0.4.0.dist-info/entry_points.txt
illallangi_mastodon-0.4.0.dist-info/licenses/LICENSE
illallangi_mastodon-0.4.0.dist-info/RECORD
